{
    "xml": "<topic id=\"PHP77974\" outputclass=\"medicinalForm\" type=\"medicinalForm\" namespace=\"/drugs/ascorbic-acid/effervescent-tablet\" basename=\"effervescent-tablet\" title=\"Effervescent tablet\">\n<title>Effervescent tablet</title>\n<body>\n<section outputclass=\"medicinalProduct\">\n<title>Haliborange Vitamin C 1000mg effervescent tablets lemon <ph outputclass=\"manufacturer\">(Seven Seas Ltd)</ph>\n</title>\n<data name=\"ampid\">11774811000001105</data>\n<p outputclass=\"strengthOfActiveIngredient\">Ascorbic acid 1&#8239;gram</p>\n<ul outputclass=\"packs\">\n<li outputclass=\"packSizePriceTariff\">\n<p outputclass=\"packInfo\">\n<ph outputclass=\"packSize\">20</ph>\n<ph outputclass=\"unitOfMeasure\">tablet</ph>\n</p>\n<p outputclass=\"nhsIndicativeInfo\">\n<ph outputclass=\"nhsIndicative\">NHS indicative</ph>\n<ph outputclass=\"priceText\">price =</ph>\n<ph outputclass=\"nhsIndicativePrice\">&#163;2.38</ph>\n</p>\n</li>\n</ul>\n</section>\n<section outputclass=\"medicinalProduct\">\n<title>Haliborange Vitamin C 1000mg effervescent tablets orange <ph outputclass=\"manufacturer\">(Seven Seas Ltd)</ph>\n</title>\n<data name=\"ampid\">11775011000001100</data>\n<p outputclass=\"strengthOfActiveIngredient\">Ascorbic acid 1&#8239;gram</p>\n<ul outputclass=\"packs\">\n<li outputclass=\"packSizePriceTariff\">\n<p outputclass=\"packInfo\">\n<ph outputclass=\"packSize\">20</ph>\n<ph outputclass=\"unitOfMeasure\">tablet</ph>\n</p>\n<p outputclass=\"nhsIndicativeInfo\">\n<ph outputclass=\"nhsIndicative\">NHS indicative</ph>\n<ph outputclass=\"priceText\">price =</ph>\n<ph outputclass=\"nhsIndicativePrice\">&#163;2.38</ph>\n</p>\n</li>\n</ul>\n</section>\n<section outputclass=\"medicinalProduct\">\n<title>Valupak Vitamin C 1000mg effervescent tablets <ph outputclass=\"manufacturer\">(BR Pharmaceuticals Ltd)</ph>\n</title>\n<data name=\"ampid\">24448411000001104</data>\n<p outputclass=\"strengthOfActiveIngredient\">Ascorbic acid 1&#8239;gram</p>\n<ul outputclass=\"packs\">\n<li outputclass=\"packSizePriceTariff\">\n<p outputclass=\"packInfo\">\n<ph outputclass=\"packSize\">20</ph>\n<ph outputclass=\"unitOfMeasure\">tablet</ph>\n</p>\n<p outputclass=\"nhsIndicativeInfo\">\n<ph outputclass=\"nhsIndicative\">NHS indicative</ph>\n<ph outputclass=\"priceText\">price =</ph>\n<ph outputclass=\"nhsIndicativePrice\">&#163;1.19</ph>\n</p>\n</li>\n</ul>\n</section>\n</body>\n<parents>\n<xref format=\"dita\" scope=\"local\" type=\"drug\" href=\"#PHP6221\" title=\"ASCORBIC ACID\" namespace=\"/drugs/ascorbic-acid\">ASCORBIC ACID</xref>\n</parents>\n</topic>",
    "id": "PHP77974",
    "outputclass": "medicinalForm",
    "type": "medicinalForm",
    "namespace": "/drugs/ascorbic-acid/effervescent-tablet",
    "basename": "effervescent-tablet",
    "form": "Effervescent tablet",
    "products": [
        {
            "title": "Haliborange Vitamin C 1000mg effervescent tablets lemon (Seven Seas Ltd) ",
            "header": "Haliborange Vitamin C 1000mg effervescent tablets lemon <ph outputclass=\"manufacturer\">(Seven Seas Ltd)</ph>",
            "manufacturer": "(Seven Seas Ltd)",
            "name": "Haliborange Vitamin C 1000mg effervescent tablets lemon",
            "ampid": "11774811000001105",
            "strengthOfActiveIngredient": "Ascorbic acid 1 gram",
            "packs": [
                {
                    "textContent": " 20 tablet ",
                    "html": "<ph outputclass=\"packSize\">20</ph> <ph outputclass=\"unitOfMeasure\">tablet</ph>",
                    "packSize": "20",
                    "unitOfMeasure": "tablet",
                    "nhsIndicativeInfo": {
                        "textContent": " NHS indicative price = &#163;2.38 ",
                        "html": "<ph outputclass=\"nhsIndicative\">NHS indicative</ph> <ph outputclass=\"priceText\">price =</ph> <ph outputclass=\"nhsIndicativePrice\">&#163;2.38</ph>",
                        "nhsIndicativePrice": "&#163;2.38"
                    }
                }
            ]
        },
        {
            "title": "Haliborange Vitamin C 1000mg effervescent tablets orange (Seven Seas Ltd) ",
            "header": "Haliborange Vitamin C 1000mg effervescent tablets orange <ph outputclass=\"manufacturer\">(Seven Seas Ltd)</ph>",
            "manufacturer": "(Seven Seas Ltd)",
            "name": "Haliborange Vitamin C 1000mg effervescent tablets orange",
            "ampid": "11775011000001100",
            "strengthOfActiveIngredient": "Ascorbic acid 1 gram",
            "packs": [
                {
                    "textContent": " 20 tablet ",
                    "html": "<ph outputclass=\"packSize\">20</ph> <ph outputclass=\"unitOfMeasure\">tablet</ph>",
                    "packSize": "20",
                    "unitOfMeasure": "tablet",
                    "nhsIndicativeInfo": {
                        "textContent": " NHS indicative price = &#163;2.38 ",
                        "html": "<ph outputclass=\"nhsIndicative\">NHS indicative</ph> <ph outputclass=\"priceText\">price =</ph> <ph outputclass=\"nhsIndicativePrice\">&#163;2.38</ph>",
                        "nhsIndicativePrice": "&#163;2.38"
                    }
                }
            ]
        },
        {
            "title": "Valupak Vitamin C 1000mg effervescent tablets (BR Pharmaceuticals Ltd) ",
            "header": "Valupak Vitamin C 1000mg effervescent tablets <ph outputclass=\"manufacturer\">(BR Pharmaceuticals Ltd)</ph>",
            "manufacturer": "(BR Pharmaceuticals Ltd)",
            "name": "Valupak Vitamin C 1000mg effervescent tablets",
            "ampid": "24448411000001104",
            "strengthOfActiveIngredient": "Ascorbic acid 1 gram",
            "packs": [
                {
                    "textContent": " 20 tablet ",
                    "html": "<ph outputclass=\"packSize\">20</ph> <ph outputclass=\"unitOfMeasure\">tablet</ph>",
                    "packSize": "20",
                    "unitOfMeasure": "tablet",
                    "nhsIndicativeInfo": {
                        "textContent": " NHS indicative price = &#163;1.19 ",
                        "html": "<ph outputclass=\"nhsIndicative\">NHS indicative</ph> <ph outputclass=\"priceText\">price =</ph> <ph outputclass=\"nhsIndicativePrice\">&#163;1.19</ph>",
                        "nhsIndicativePrice": "&#163;1.19"
                    }
                }
            ]
        }
    ],
    "parent": {
        "id": "PHP6221",
        "label": "ASCORBIC ACID"
    }
}