{
    "xml": "<topic id=\"PHP77850\" outputclass=\"medicinalForm\" type=\"medicinalForm\" namespace=\"/drugs/valproic-acid/gastro-resistant-capsule\" basename=\"gastro-resistant-capsule\" title=\"Gastro-resistant capsule\">\n<title>Gastro-resistant capsule</title>\n<body>\r\n<section outputclass=\"cautionaryAndAdvisoryLabels\">\r\n<title>Cautionary and advisory labels</title>\r\n<p>Label <ph outputclass=\"labelNumber\">8</ph> - Warning: Do not stop taking this medicine unless your doctor tells you to stop </p>\r\n<p>Label <ph outputclass=\"labelNumber\">21</ph> - Take with or just after food, or a meal </p>\r\n<p>Label <ph outputclass=\"labelNumber\">25</ph> - Swallow this medicine whole. Do not chew or crush </p>\r\n<p>Label <ph outputclass=\"labelNumber\">10</ph> - Warning: Read the additional information given with this medicine </p>\n</section>\r\n\r\n\r\n<section outputclass=\"clinicalMedicinalProductInformationGroup\">\n<xref format=\"dita\" href=\"#PHP80911\" outputclass=\"clinicalMedicinalProductInformationXref\" namespace=\"/clinical-medicinal-product-information/convulex\">Convulex<tm tmtype=\"reg\"/>\r\n</xref>\n</section>\r\n<section outputclass=\"medicinalProduct\">\r\n<title>Convulex 150mg gastro-resistant capsules <ph outputclass=\"manufacturer\">(Pfizer Ltd)</ph>\n<ph outputclass=\"blackTriangle\">&#9660;</ph>\r\n</title>\n<data name=\"ampid\">3920911000001105</data>\r\n<p outputclass=\"strengthOfActiveIngredient\">Valproic acid 150&#8239;mg</p>\r\n<ul outputclass=\"packs\">\r\n<li outputclass=\"packSizePriceTariff\">\r\n<p outputclass=\"packInfo\">\r\n<ph outputclass=\"packSize\">100</ph>\n<ph outputclass=\"unitOfMeasure\">capsule</ph>\n<ph outputclass=\"legalCategory\">POM</ph>\r\n</p>\r\n<p outputclass=\"nhsIndicativeInfo\">\n<ph outputclass=\"nhsIndicative\">NHS indicative</ph>\n<ph outputclass=\"priceText\">price =</ph>\n<ph outputclass=\"nhsIndicativePrice\">&#163;3.68</ph>\n</p>\n</li>\r\n</ul>\n</section>\r\n<section outputclass=\"medicinalProduct\">\r\n<title>Convulex 300mg gastro-resistant capsules <ph outputclass=\"manufacturer\">(Pfizer Ltd)</ph>\n<ph outputclass=\"blackTriangle\">&#9660;</ph>\r\n</title>\n<data name=\"ampid\">3921311000001104</data>\r\n<p outputclass=\"strengthOfActiveIngredient\">Valproic acid 300&#8239;mg</p>\r\n<ul outputclass=\"packs\">\r\n<li outputclass=\"packSizePriceTariff\">\r\n<p outputclass=\"packInfo\">\r\n<ph outputclass=\"packSize\">100</ph>\n<ph outputclass=\"unitOfMeasure\">capsule</ph>\n<ph outputclass=\"legalCategory\">POM</ph>\r\n</p>\r\n<p outputclass=\"nhsIndicativeInfo\">\n<ph outputclass=\"nhsIndicative\">NHS indicative</ph>\n<ph outputclass=\"priceText\">price =</ph>\n<ph outputclass=\"nhsIndicativePrice\">&#163;7.35</ph>\n</p>\n</li>\r\n</ul>\n</section>\r\n<section outputclass=\"medicinalProduct\">\r\n<title>Convulex 500mg gastro-resistant capsules <ph outputclass=\"manufacturer\">(Pfizer Ltd)</ph>\n<ph outputclass=\"blackTriangle\">&#9660;</ph>\r\n</title>\n<data name=\"ampid\">3921711000001100</data>\r\n<p outputclass=\"strengthOfActiveIngredient\">Valproic acid 500&#8239;mg</p>\r\n<ul outputclass=\"packs\">\r\n<li outputclass=\"packSizePriceTariff\">\r\n<p outputclass=\"packInfo\">\r\n<ph outputclass=\"packSize\">100</ph>\n<ph outputclass=\"unitOfMeasure\">capsule</ph>\n<ph outputclass=\"legalCategory\">POM</ph>\r\n</p>\r\n<p outputclass=\"nhsIndicativeInfo\">\n<ph outputclass=\"nhsIndicative\">NHS indicative</ph>\n<ph outputclass=\"priceText\">price =</ph>\n<ph outputclass=\"nhsIndicativePrice\">&#163;12.25</ph>\n</p>\n</li>\r\n</ul>\n</section>\r\n</body>\n<parents>\n<xref format=\"dita\" scope=\"local\" type=\"drug\" href=\"#PHP2331\" title=\"VALPROIC ACID\" namespace=\"/drugs/valproic-acid\">VALPROIC ACID</xref>\n</parents>\n</topic>",
    "id": "PHP77850",
    "outputclass": "medicinalForm",
    "type": "medicinalForm",
    "namespace": "/drugs/valproic-acid/gastro-resistant-capsule",
    "basename": "gastro-resistant-capsule",
    "form": "Gastro-resistant capsule",
    "cautionaryAndAdvisoryLabels": [
        {
            "number": "8",
            "textContent": "Warning: Do not stop taking this medicine unless your doctor tells you to stop",
            "html": "Label <ph outputclass=\"labelNumber\">8</ph> - Warning: Do not stop taking this medicine unless your doctor tells you to stop"
        },
        {
            "number": "21",
            "textContent": "Take with or just after food, or a meal",
            "html": "Label <ph outputclass=\"labelNumber\">21</ph> - Take with or just after food, or a meal"
        },
        {
            "number": "25",
            "textContent": "Swallow this medicine whole. Do not chew or crush",
            "html": "Label <ph outputclass=\"labelNumber\">25</ph> - Swallow this medicine whole. Do not chew or crush"
        },
        {
            "number": "10",
            "textContent": "Warning: Read the additional information given with this medicine",
            "html": "Label <ph outputclass=\"labelNumber\">10</ph> - Warning: Read the additional information given with this medicine"
        }
    ],
    "productInformationGroups": [
        {
            "id": "PHP80911",
            "label": "Convulex&reg;  ",
            "html": "Convulex<tm tmtype=\"reg\"/>"
        }
    ],
    "products": [
        {
            "title": "Convulex 150mg gastro-resistant capsules (Pfizer Ltd) &#9660; ",
            "header": "Convulex 150mg gastro-resistant capsules <ph outputclass=\"manufacturer\">(Pfizer Ltd)</ph> <ph outputclass=\"blackTriangle\">&#9660;</ph>",
            "manufacturer": "(Pfizer Ltd)",
            "blackTriangle": "&#9660;",
            "name": "Convulex 150mg gastro-resistant capsules",
            "ampid": "3920911000001105",
            "strengthOfActiveIngredient": "Valproic acid 150 mg",
            "packs": [
                {
                    "textContent": " 100 capsule POM ",
                    "html": "<ph outputclass=\"packSize\">100</ph> <ph outputclass=\"unitOfMeasure\">capsule</ph> <ph outputclass=\"legalCategory\">POM</ph>",
                    "packSize": "100",
                    "unitOfMeasure": "capsule",
                    "legalCategory": "POM",
                    "nhsIndicativeInfo": {
                        "textContent": " NHS indicative price = &#163;3.68 ",
                        "html": "<ph outputclass=\"nhsIndicative\">NHS indicative</ph> <ph outputclass=\"priceText\">price =</ph> <ph outputclass=\"nhsIndicativePrice\">&#163;3.68</ph>",
                        "nhsIndicativePrice": "&#163;3.68"
                    }
                }
            ]
        },
        {
            "title": "Convulex 300mg gastro-resistant capsules (Pfizer Ltd) &#9660; ",
            "header": "Convulex 300mg gastro-resistant capsules <ph outputclass=\"manufacturer\">(Pfizer Ltd)</ph> <ph outputclass=\"blackTriangle\">&#9660;</ph>",
            "manufacturer": "(Pfizer Ltd)",
            "blackTriangle": "&#9660;",
            "name": "Convulex 300mg gastro-resistant capsules",
            "ampid": "3921311000001104",
            "strengthOfActiveIngredient": "Valproic acid 300 mg",
            "packs": [
                {
                    "textContent": " 100 capsule POM ",
                    "html": "<ph outputclass=\"packSize\">100</ph> <ph outputclass=\"unitOfMeasure\">capsule</ph> <ph outputclass=\"legalCategory\">POM</ph>",
                    "packSize": "100",
                    "unitOfMeasure": "capsule",
                    "legalCategory": "POM",
                    "nhsIndicativeInfo": {
                        "textContent": " NHS indicative price = &#163;7.35 ",
                        "html": "<ph outputclass=\"nhsIndicative\">NHS indicative</ph> <ph outputclass=\"priceText\">price =</ph> <ph outputclass=\"nhsIndicativePrice\">&#163;7.35</ph>",
                        "nhsIndicativePrice": "&#163;7.35"
                    }
                }
            ]
        },
        {
            "title": "Convulex 500mg gastro-resistant capsules (Pfizer Ltd) &#9660; ",
            "header": "Convulex 500mg gastro-resistant capsules <ph outputclass=\"manufacturer\">(Pfizer Ltd)</ph> <ph outputclass=\"blackTriangle\">&#9660;</ph>",
            "manufacturer": "(Pfizer Ltd)",
            "blackTriangle": "&#9660;",
            "name": "Convulex 500mg gastro-resistant capsules",
            "ampid": "3921711000001100",
            "strengthOfActiveIngredient": "Valproic acid 500 mg",
            "packs": [
                {
                    "textContent": " 100 capsule POM ",
                    "html": "<ph outputclass=\"packSize\">100</ph> <ph outputclass=\"unitOfMeasure\">capsule</ph> <ph outputclass=\"legalCategory\">POM</ph>",
                    "packSize": "100",
                    "unitOfMeasure": "capsule",
                    "legalCategory": "POM",
                    "nhsIndicativeInfo": {
                        "textContent": " NHS indicative price = &#163;12.25 ",
                        "html": "<ph outputclass=\"nhsIndicative\">NHS indicative</ph> <ph outputclass=\"priceText\">price =</ph> <ph outputclass=\"nhsIndicativePrice\">&#163;12.25</ph>",
                        "nhsIndicativePrice": "&#163;12.25"
                    }
                }
            ]
        }
    ],
    "parent": {
        "id": "PHP2331",
        "label": "VALPROIC ACID"
    }
}