{
    "xml": "<topic id=\"PHP74612\" outputclass=\"medicinalForm\" type=\"medicinalForm\" namespace=\"/drugs/hydrocortisone/powder-and-solvent-for-solution-for-injection\" basename=\"powder-and-solvent-for-solution-for-injection\" title=\"Powder and solvent for solution for injection\">\n<title>Powder and solvent for solution for injection</title>\n<body>\n<section outputclass=\"cautionaryAndAdvisoryLabels\">\n<title>Cautionary and advisory labels</title>\n<p>Label <ph outputclass=\"labelNumber\">10</ph> - Warning: Read the additional information given with this medicine </p>\n</section>\n<section outputclass=\"medicinalProduct\">\n<title>Solu-Cortef 100mg powder and solvent for solution for injection vials <ph outputclass=\"manufacturer\">(Pfizer Ltd)</ph>\n</title>\n<data name=\"ampid\">4182611000001108</data>\n<p outputclass=\"strengthOfActiveIngredient\">Hydrocortisone (as Hydrocortisone sodium succinate) 100&#8239;mg</p>\n<ul outputclass=\"packs\">\n<li outputclass=\"packSizePriceTariff\">\n<p outputclass=\"packInfo\">\n<ph outputclass=\"packSize\">1</ph>\n<ph outputclass=\"unitOfMeasure\">vial</ph>\n<ph outputclass=\"legalCategory\">POM</ph>\n</p>\n<p outputclass=\"nhsIndicativeInfo\">\n<ph outputclass=\"nhsIndicative\">NHS indicative</ph>\n<ph outputclass=\"priceText\">price =</ph>\n<ph outputclass=\"nhsIndicativePrice\">&#163;1.16</ph>\n</p>\n<p outputclass=\"drugTariffInfo\">\n<ph outputclass=\"drugTariff\">Drug Tariff (Part VIIIA Category C)</ph>\n<ph outputclass=\"priceText\">price =</ph>\n<ph outputclass=\"drugTariffPrice\">&#163;1.16</ph>\n</p>\n</li>\n</ul>\n</section>\n</body>\n<parents>\n<xref format=\"dita\" scope=\"local\" type=\"drug\" href=\"#PHP515\" title=\"HYDROCORTISONE\" namespace=\"/drugs/hydrocortisone\">HYDROCORTISONE</xref>\n</parents>\n</topic>",
    "id": "PHP74612",
    "outputclass": "medicinalForm",
    "type": "medicinalForm",
    "namespace": "/drugs/hydrocortisone/powder-and-solvent-for-solution-for-injection",
    "basename": "powder-and-solvent-for-solution-for-injection",
    "form": "Powder and solvent for solution for injection",
    "cautionaryAndAdvisoryLabels": [
        {
            "number": "10",
            "textContent": "Warning: Read the additional information given with this medicine",
            "html": "Label <ph outputclass=\"labelNumber\">10</ph> - Warning: Read the additional information given with this medicine"
        }
    ],
    "products": [
        {
            "title": "Solu-Cortef 100mg powder and solvent for solution for injection vials (Pfizer Ltd) ",
            "header": "Solu-Cortef 100mg powder and solvent for solution for injection vials <ph outputclass=\"manufacturer\">(Pfizer Ltd)</ph>",
            "manufacturer": "(Pfizer Ltd)",
            "name": "Solu-Cortef 100mg powder and solvent for solution for injection vials",
            "ampid": "4182611000001108",
            "strengthOfActiveIngredient": "Hydrocortisone (as Hydrocortisone sodium succinate) 100 mg",
            "packs": [
                {
                    "textContent": " 1 vial POM ",
                    "html": "<ph outputclass=\"packSize\">1</ph> <ph outputclass=\"unitOfMeasure\">vial</ph> <ph outputclass=\"legalCategory\">POM</ph>",
                    "packSize": "1",
                    "unitOfMeasure": "vial",
                    "legalCategory": "POM",
                    "nhsIndicativeInfo": {
                        "textContent": " NHS indicative price = &#163;1.16 ",
                        "html": "<ph outputclass=\"nhsIndicative\">NHS indicative</ph> <ph outputclass=\"priceText\">price =</ph> <ph outputclass=\"nhsIndicativePrice\">&#163;1.16</ph>",
                        "nhsIndicativePrice": "&#163;1.16"
                    },
                    "drugTariffInfo": {
                        "textContent": " Drug Tariff (Part VIIIA Category C) price = &#163;1.16 ",
                        "html": "<ph outputclass=\"drugTariff\">Drug Tariff (Part VIIIA Category C)</ph> <ph outputclass=\"priceText\">price =</ph> <ph outputclass=\"drugTariffPrice\">&#163;1.16</ph>",
                        "drugTariff": "Drug Tariff (Part VIIIA Category C)",
                        "drugTariffPrice": "&#163;1.16"
                    }
                }
            ]
        }
    ],
    "parent": {
        "id": "PHP515",
        "label": "HYDROCORTISONE"
    }
}