{
    "xml": "<topic id=\"PHP75721\" outputclass=\"medicinalForm\" type=\"medicinalForm\" namespace=\"/drugs/oxaliplatin/powder-for-solution-for-infusion\" basename=\"powder-for-solution-for-infusion\" title=\"Powder for solution for infusion\">\n<title>Powder for solution for infusion</title>\n<body>\n<section outputclass=\"medicinalProduct\">\n<title>Oxaliplatin 50mg powder for solution for infusion vials <ph outputclass=\"manufacturer\">(Hospira UK Ltd)</ph>\n</title>\n<data name=\"ampid\">10907011000001104</data>\n<p outputclass=\"strengthOfActiveIngredient\">Oxaliplatin 50&#8239;mg</p>\n<ul outputclass=\"packs\">\n<li outputclass=\"packSizePriceTariff\">\n<p outputclass=\"packInfo\">\n<ph outputclass=\"packSize\">1</ph>\n<ph outputclass=\"unitOfMeasure\">vial</ph>\n<ph outputclass=\"legalCategory\">POM</ph>\n</p>\n<p outputclass=\"nhsIndicativeInfo\">\n<ph outputclass=\"nhsIndicative\">NHS indicative</ph>\n<ph outputclass=\"priceText\">price =</ph>\n<ph outputclass=\"nhsIndicativePrice\">&#163;156.75</ph>\n</p>\n</li>\n</ul>\n</section>\n<section outputclass=\"medicinalProduct\">\n<title>Oxaliplatin 50mg powder for solution for infusion vials <ph outputclass=\"manufacturer\">(Mylan Ltd)</ph>\n</title>\n<data name=\"ampid\">16100711000001106</data>\n<p outputclass=\"strengthOfActiveIngredient\">Oxaliplatin 50&#8239;mg</p>\n<ul outputclass=\"packs\">\n<li outputclass=\"packSizePriceTariff\">\n<p outputclass=\"packInfo\">\n<ph outputclass=\"packSize\">1</ph>\n<ph outputclass=\"unitOfMeasure\">vial</ph>\n<ph outputclass=\"legalCategory\">POM</ph>\n</p>\n<p outputclass=\"nhsIndicativeInfo\">\n<ph outputclass=\"nhsIndicative\">NHS indicative</ph>\n<ph outputclass=\"priceText\">price =</ph>\n<ph outputclass=\"nhsIndicativePrice\">&#163;150.00</ph>\n</p>\n</li>\n</ul>\n</section>\n<section outputclass=\"medicinalProduct\">\n<title>Oxaliplatin 100mg powder for solution for infusion vials <ph outputclass=\"manufacturer\">(Hospira UK Ltd)</ph>\n</title>\n<data name=\"ampid\">10907211000001109</data>\n<p outputclass=\"strengthOfActiveIngredient\">Oxaliplatin 100&#8239;mg</p>\n<ul outputclass=\"packs\">\n<li outputclass=\"packSizePriceTariff\">\n<p outputclass=\"packInfo\">\n<ph outputclass=\"packSize\">1</ph>\n<ph outputclass=\"unitOfMeasure\">vial</ph>\n<ph outputclass=\"legalCategory\">POM</ph>\n</p>\n<p outputclass=\"nhsIndicativeInfo\">\n<ph outputclass=\"nhsIndicative\">NHS indicative</ph>\n<ph outputclass=\"priceText\">price =</ph>\n<ph outputclass=\"nhsIndicativePrice\">&#163;313.50</ph>\n</p>\n</li>\n</ul>\n</section>\n<section outputclass=\"medicinalProduct\">\n<title>Oxaliplatin 100mg powder for solution for infusion vials <ph outputclass=\"manufacturer\">(Mylan Ltd)</ph>\n</title>\n<data name=\"ampid\">16100511000001101</data>\n<p outputclass=\"strengthOfActiveIngredient\">Oxaliplatin 100&#8239;mg</p>\n<ul outputclass=\"packs\">\n<li outputclass=\"packSizePriceTariff\">\n<p outputclass=\"packInfo\">\n<ph outputclass=\"packSize\">1</ph>\n<ph outputclass=\"unitOfMeasure\">vial</ph>\n<ph outputclass=\"legalCategory\">POM</ph>\n</p>\n<p outputclass=\"nhsIndicativeInfo\">\n<ph outputclass=\"nhsIndicative\">NHS indicative</ph>\n<ph outputclass=\"priceText\">price =</ph>\n<ph outputclass=\"nhsIndicativePrice\">&#163;299.50</ph>\n</p>\n</li>\n</ul>\n</section>\n</body>\n<parents>\n<xref format=\"dita\" scope=\"local\" type=\"drug\" href=\"#PHP5501\" title=\"OXALIPLATIN\" namespace=\"/drugs/oxaliplatin\">OXALIPLATIN</xref>\n</parents>\n</topic>",
    "id": "PHP75721",
    "outputclass": "medicinalForm",
    "type": "medicinalForm",
    "namespace": "/drugs/oxaliplatin/powder-for-solution-for-infusion",
    "basename": "powder-for-solution-for-infusion",
    "form": "Powder for solution for infusion",
    "products": [
        {
            "title": "Oxaliplatin 50mg powder for solution for infusion vials (Hospira UK Ltd) ",
            "header": "Oxaliplatin 50mg powder for solution for infusion vials <ph outputclass=\"manufacturer\">(Hospira UK Ltd)</ph>",
            "manufacturer": "(Hospira UK Ltd)",
            "name": "Oxaliplatin 50mg powder for solution for infusion vials",
            "ampid": "10907011000001104",
            "strengthOfActiveIngredient": "Oxaliplatin 50 mg",
            "packs": [
                {
                    "textContent": " 1 vial POM ",
                    "html": "<ph outputclass=\"packSize\">1</ph> <ph outputclass=\"unitOfMeasure\">vial</ph> <ph outputclass=\"legalCategory\">POM</ph>",
                    "packSize": "1",
                    "unitOfMeasure": "vial",
                    "legalCategory": "POM",
                    "nhsIndicativeInfo": {
                        "textContent": " NHS indicative price = &#163;156.75 ",
                        "html": "<ph outputclass=\"nhsIndicative\">NHS indicative</ph> <ph outputclass=\"priceText\">price =</ph> <ph outputclass=\"nhsIndicativePrice\">&#163;156.75</ph>",
                        "nhsIndicativePrice": "&#163;156.75"
                    }
                }
            ]
        },
        {
            "title": "Oxaliplatin 50mg powder for solution for infusion vials (Mylan Ltd) ",
            "header": "Oxaliplatin 50mg powder for solution for infusion vials <ph outputclass=\"manufacturer\">(Mylan Ltd)</ph>",
            "manufacturer": "(Mylan Ltd)",
            "name": "Oxaliplatin 50mg powder for solution for infusion vials",
            "ampid": "16100711000001106",
            "strengthOfActiveIngredient": "Oxaliplatin 50 mg",
            "packs": [
                {
                    "textContent": " 1 vial POM ",
                    "html": "<ph outputclass=\"packSize\">1</ph> <ph outputclass=\"unitOfMeasure\">vial</ph> <ph outputclass=\"legalCategory\">POM</ph>",
                    "packSize": "1",
                    "unitOfMeasure": "vial",
                    "legalCategory": "POM",
                    "nhsIndicativeInfo": {
                        "textContent": " NHS indicative price = &#163;150.00 ",
                        "html": "<ph outputclass=\"nhsIndicative\">NHS indicative</ph> <ph outputclass=\"priceText\">price =</ph> <ph outputclass=\"nhsIndicativePrice\">&#163;150.00</ph>",
                        "nhsIndicativePrice": "&#163;150.00"
                    }
                }
            ]
        },
        {
            "title": "Oxaliplatin 100mg powder for solution for infusion vials (Hospira UK Ltd) ",
            "header": "Oxaliplatin 100mg powder for solution for infusion vials <ph outputclass=\"manufacturer\">(Hospira UK Ltd)</ph>",
            "manufacturer": "(Hospira UK Ltd)",
            "name": "Oxaliplatin 100mg powder for solution for infusion vials",
            "ampid": "10907211000001109",
            "strengthOfActiveIngredient": "Oxaliplatin 100 mg",
            "packs": [
                {
                    "textContent": " 1 vial POM ",
                    "html": "<ph outputclass=\"packSize\">1</ph> <ph outputclass=\"unitOfMeasure\">vial</ph> <ph outputclass=\"legalCategory\">POM</ph>",
                    "packSize": "1",
                    "unitOfMeasure": "vial",
                    "legalCategory": "POM",
                    "nhsIndicativeInfo": {
                        "textContent": " NHS indicative price = &#163;313.50 ",
                        "html": "<ph outputclass=\"nhsIndicative\">NHS indicative</ph> <ph outputclass=\"priceText\">price =</ph> <ph outputclass=\"nhsIndicativePrice\">&#163;313.50</ph>",
                        "nhsIndicativePrice": "&#163;313.50"
                    }
                }
            ]
        },
        {
            "title": "Oxaliplatin 100mg powder for solution for infusion vials (Mylan Ltd) ",
            "header": "Oxaliplatin 100mg powder for solution for infusion vials <ph outputclass=\"manufacturer\">(Mylan Ltd)</ph>",
            "manufacturer": "(Mylan Ltd)",
            "name": "Oxaliplatin 100mg powder for solution for infusion vials",
            "ampid": "16100511000001101",
            "strengthOfActiveIngredient": "Oxaliplatin 100 mg",
            "packs": [
                {
                    "textContent": " 1 vial POM ",
                    "html": "<ph outputclass=\"packSize\">1</ph> <ph outputclass=\"unitOfMeasure\">vial</ph> <ph outputclass=\"legalCategory\">POM</ph>",
                    "packSize": "1",
                    "unitOfMeasure": "vial",
                    "legalCategory": "POM",
                    "nhsIndicativeInfo": {
                        "textContent": " NHS indicative price = &#163;299.50 ",
                        "html": "<ph outputclass=\"nhsIndicative\">NHS indicative</ph> <ph outputclass=\"priceText\">price =</ph> <ph outputclass=\"nhsIndicativePrice\">&#163;299.50</ph>",
                        "nhsIndicativePrice": "&#163;299.50"
                    }
                }
            ]
        }
    ],
    "parent": {
        "id": "PHP5501",
        "label": "OXALIPLATIN"
    }
}