{
    "xml": "<topic id=\"PHP76136\" outputclass=\"medicinalForm\" type=\"medicinalForm\" namespace=\"/drugs/mometasone-furoate/inhalation-powder\" basename=\"inhalation-powder\" title=\"Inhalation powder\">\n<title>Inhalation powder</title>\n<body>\n<section outputclass=\"cautionaryAndAdvisoryLabels\">\n<title>Cautionary and advisory labels</title>\n<p>Label <ph outputclass=\"labelNumber\">8</ph> - Warning: Do not stop taking this medicine unless your doctor tells you to stop </p>\n<p>Label <ph outputclass=\"labelNumber\">10</ph> - Warning: Read the additional information given with this medicine </p>\n</section>\n<section outputclass=\"medicinalProduct\">\n<title>Asmanex 200micrograms/dose Twisthaler <ph outputclass=\"manufacturer\">(Merck Sharp &amp; Dohme Ltd)</ph>\n</title>\n<data name=\"ampid\">4045711000001107</data>\n<p outputclass=\"strengthOfActiveIngredient\">Mometasone furoate 200&#8239;microgram per 1&#8239;dose</p>\n<ul outputclass=\"packs\">\n<li outputclass=\"packSizePriceTariff\">\n<p outputclass=\"packInfo\">\n<ph outputclass=\"packSize\">30</ph>\n<ph outputclass=\"unitOfMeasure\">dose</ph>\n<ph outputclass=\"legalCategory\">POM</ph>\n</p>\n<p outputclass=\"nhsIndicativeInfo\">\n<ph outputclass=\"nhsIndicative\">NHS indicative</ph>\n<ph outputclass=\"priceText\">price =</ph>\n<ph outputclass=\"nhsIndicativePrice\">&#163;15.70</ph>\n</p>\n<p outputclass=\"drugTariffInfo\">\n<ph outputclass=\"drugTariff\">Drug Tariff (Part VIIIA Category C)</ph>\n<ph outputclass=\"priceText\">price =</ph>\n<ph outputclass=\"drugTariffPrice\">&#163;15.70</ph>\n</p>\n</li>\n<li outputclass=\"packSizePriceTariff\">\n<p outputclass=\"packInfo\">\n<ph outputclass=\"packSize\">60</ph>\n<ph outputclass=\"unitOfMeasure\">dose</ph>\n<ph outputclass=\"legalCategory\">POM</ph>\n</p>\n<p outputclass=\"nhsIndicativeInfo\">\n<ph outputclass=\"nhsIndicative\">NHS indicative</ph>\n<ph outputclass=\"priceText\">price =</ph>\n<ph outputclass=\"nhsIndicativePrice\">&#163;23.54</ph>\n</p>\n<p outputclass=\"drugTariffInfo\">\n<ph outputclass=\"drugTariff\">Drug Tariff (Part VIIIA Category C)</ph>\n<ph outputclass=\"priceText\">price =</ph>\n<ph outputclass=\"drugTariffPrice\">&#163;23.54</ph>\n</p>\n</li>\n</ul>\n</section>\n<section outputclass=\"medicinalProduct\">\n<title>Asmanex 400micrograms/dose Twisthaler <ph outputclass=\"manufacturer\">(Merck Sharp &amp; Dohme Ltd)</ph>\n</title>\n<data name=\"ampid\">4043811000001103</data>\n<p outputclass=\"strengthOfActiveIngredient\">Mometasone furoate 400&#8239;microgram per 1&#8239;dose</p>\n<ul outputclass=\"packs\">\n<li outputclass=\"packSizePriceTariff\">\n<p outputclass=\"packInfo\">\n<ph outputclass=\"packSize\">30</ph>\n<ph outputclass=\"unitOfMeasure\">dose</ph>\n<ph outputclass=\"legalCategory\">POM</ph>\n</p>\n<p outputclass=\"nhsIndicativeInfo\">\n<ph outputclass=\"nhsIndicative\">NHS indicative</ph>\n<ph outputclass=\"priceText\">price =</ph>\n<ph outputclass=\"nhsIndicativePrice\">&#163;21.78</ph>\n</p>\n<p outputclass=\"drugTariffInfo\">\n<ph outputclass=\"drugTariff\">Drug Tariff (Part VIIIA Category C)</ph>\n<ph outputclass=\"priceText\">price =</ph>\n<ph outputclass=\"drugTariffPrice\">&#163;21.78</ph>\n</p>\n</li>\n<li outputclass=\"packSizePriceTariff\">\n<p outputclass=\"packInfo\">\n<ph outputclass=\"packSize\">60</ph>\n<ph outputclass=\"unitOfMeasure\">dose</ph>\n<ph outputclass=\"legalCategory\">POM</ph>\n</p>\n<p outputclass=\"nhsIndicativeInfo\">\n<ph outputclass=\"nhsIndicative\">NHS indicative</ph>\n<ph outputclass=\"priceText\">price =</ph>\n<ph outputclass=\"nhsIndicativePrice\">&#163;36.05</ph>\n</p>\n<p outputclass=\"drugTariffInfo\">\n<ph outputclass=\"drugTariff\">Drug Tariff (Part VIIIA Category C)</ph>\n<ph outputclass=\"priceText\">price =</ph>\n<ph outputclass=\"drugTariffPrice\">&#163;36.05</ph>\n</p>\n</li>\n</ul>\n</section>\n</body>\n<parents>\n<xref format=\"dita\" scope=\"local\" type=\"drug\" href=\"#PHP1875\" title=\"MOMETASONE FUROATE\" namespace=\"/drugs/mometasone-furoate\">MOMETASONE FUROATE</xref>\n</parents>\n</topic>",
    "id": "PHP76136",
    "outputclass": "medicinalForm",
    "type": "medicinalForm",
    "namespace": "/drugs/mometasone-furoate/inhalation-powder",
    "basename": "inhalation-powder",
    "form": "Inhalation powder",
    "cautionaryAndAdvisoryLabels": [
        {
            "number": "8",
            "textContent": "Warning: Do not stop taking this medicine unless your doctor tells you to stop",
            "html": "Label <ph outputclass=\"labelNumber\">8</ph> - Warning: Do not stop taking this medicine unless your doctor tells you to stop"
        },
        {
            "number": "10",
            "textContent": "Warning: Read the additional information given with this medicine",
            "html": "Label <ph outputclass=\"labelNumber\">10</ph> - Warning: Read the additional information given with this medicine"
        }
    ],
    "products": [
        {
            "title": "Asmanex 200micrograms/dose Twisthaler (Merck Sharp & Dohme Ltd) ",
            "header": "Asmanex 200micrograms/dose Twisthaler <ph outputclass=\"manufacturer\">(Merck Sharp &amp; Dohme Ltd)</ph>",
            "manufacturer": "(Merck Sharp & Dohme Ltd)",
            "name": "Asmanex 200micrograms/dose Twisthaler",
            "ampid": "4045711000001107",
            "strengthOfActiveIngredient": "Mometasone furoate 200 microgram per 1 dose",
            "packs": [
                {
                    "textContent": " 30 dose POM ",
                    "html": "<ph outputclass=\"packSize\">30</ph> <ph outputclass=\"unitOfMeasure\">dose</ph> <ph outputclass=\"legalCategory\">POM</ph>",
                    "packSize": "30",
                    "unitOfMeasure": "dose",
                    "legalCategory": "POM",
                    "nhsIndicativeInfo": {
                        "textContent": " NHS indicative price = &#163;15.70 ",
                        "html": "<ph outputclass=\"nhsIndicative\">NHS indicative</ph> <ph outputclass=\"priceText\">price =</ph> <ph outputclass=\"nhsIndicativePrice\">&#163;15.70</ph>",
                        "nhsIndicativePrice": "&#163;15.70"
                    },
                    "drugTariffInfo": {
                        "textContent": " Drug Tariff (Part VIIIA Category C) price = &#163;15.70 ",
                        "html": "<ph outputclass=\"drugTariff\">Drug Tariff (Part VIIIA Category C)</ph> <ph outputclass=\"priceText\">price =</ph> <ph outputclass=\"drugTariffPrice\">&#163;15.70</ph>",
                        "drugTariff": "Drug Tariff (Part VIIIA Category C)",
                        "drugTariffPrice": "&#163;15.70"
                    }
                },
                {
                    "textContent": " 60 dose POM ",
                    "html": "<ph outputclass=\"packSize\">60</ph> <ph outputclass=\"unitOfMeasure\">dose</ph> <ph outputclass=\"legalCategory\">POM</ph>",
                    "packSize": "60",
                    "unitOfMeasure": "dose",
                    "legalCategory": "POM",
                    "nhsIndicativeInfo": {
                        "textContent": " NHS indicative price = &#163;23.54 ",
                        "html": "<ph outputclass=\"nhsIndicative\">NHS indicative</ph> <ph outputclass=\"priceText\">price =</ph> <ph outputclass=\"nhsIndicativePrice\">&#163;23.54</ph>",
                        "nhsIndicativePrice": "&#163;23.54"
                    },
                    "drugTariffInfo": {
                        "textContent": " Drug Tariff (Part VIIIA Category C) price = &#163;23.54 ",
                        "html": "<ph outputclass=\"drugTariff\">Drug Tariff (Part VIIIA Category C)</ph> <ph outputclass=\"priceText\">price =</ph> <ph outputclass=\"drugTariffPrice\">&#163;23.54</ph>",
                        "drugTariff": "Drug Tariff (Part VIIIA Category C)",
                        "drugTariffPrice": "&#163;23.54"
                    }
                }
            ]
        },
        {
            "title": "Asmanex 400micrograms/dose Twisthaler (Merck Sharp & Dohme Ltd) ",
            "header": "Asmanex 400micrograms/dose Twisthaler <ph outputclass=\"manufacturer\">(Merck Sharp &amp; Dohme Ltd)</ph>",
            "manufacturer": "(Merck Sharp & Dohme Ltd)",
            "name": "Asmanex 400micrograms/dose Twisthaler",
            "ampid": "4043811000001103",
            "strengthOfActiveIngredient": "Mometasone furoate 400 microgram per 1 dose",
            "packs": [
                {
                    "textContent": " 30 dose POM ",
                    "html": "<ph outputclass=\"packSize\">30</ph> <ph outputclass=\"unitOfMeasure\">dose</ph> <ph outputclass=\"legalCategory\">POM</ph>",
                    "packSize": "30",
                    "unitOfMeasure": "dose",
                    "legalCategory": "POM",
                    "nhsIndicativeInfo": {
                        "textContent": " NHS indicative price = &#163;21.78 ",
                        "html": "<ph outputclass=\"nhsIndicative\">NHS indicative</ph> <ph outputclass=\"priceText\">price =</ph> <ph outputclass=\"nhsIndicativePrice\">&#163;21.78</ph>",
                        "nhsIndicativePrice": "&#163;21.78"
                    },
                    "drugTariffInfo": {
                        "textContent": " Drug Tariff (Part VIIIA Category C) price = &#163;21.78 ",
                        "html": "<ph outputclass=\"drugTariff\">Drug Tariff (Part VIIIA Category C)</ph> <ph outputclass=\"priceText\">price =</ph> <ph outputclass=\"drugTariffPrice\">&#163;21.78</ph>",
                        "drugTariff": "Drug Tariff (Part VIIIA Category C)",
                        "drugTariffPrice": "&#163;21.78"
                    }
                },
                {
                    "textContent": " 60 dose POM ",
                    "html": "<ph outputclass=\"packSize\">60</ph> <ph outputclass=\"unitOfMeasure\">dose</ph> <ph outputclass=\"legalCategory\">POM</ph>",
                    "packSize": "60",
                    "unitOfMeasure": "dose",
                    "legalCategory": "POM",
                    "nhsIndicativeInfo": {
                        "textContent": " NHS indicative price = &#163;36.05 ",
                        "html": "<ph outputclass=\"nhsIndicative\">NHS indicative</ph> <ph outputclass=\"priceText\">price =</ph> <ph outputclass=\"nhsIndicativePrice\">&#163;36.05</ph>",
                        "nhsIndicativePrice": "&#163;36.05"
                    },
                    "drugTariffInfo": {
                        "textContent": " Drug Tariff (Part VIIIA Category C) price = &#163;36.05 ",
                        "html": "<ph outputclass=\"drugTariff\">Drug Tariff (Part VIIIA Category C)</ph> <ph outputclass=\"priceText\">price =</ph> <ph outputclass=\"drugTariffPrice\">&#163;36.05</ph>",
                        "drugTariff": "Drug Tariff (Part VIIIA Category C)",
                        "drugTariffPrice": "&#163;36.05"
                    }
                }
            ]
        }
    ],
    "parent": {
        "id": "PHP1875",
        "label": "MOMETASONE FUROATE"
    }
}