{
    "xml": "<topic id=\"PHP76215\" outputclass=\"medicinalForm\" type=\"medicinalForm\" namespace=\"/drugs/azelastine-hydrochloride/eye-drops\" basename=\"eye-drops\" title=\"Eye drops\">\n<title>Eye drops</title>\n<body>\n<section outputclass=\"excipients\">\n<title>Excipients</title>\n<p outputclass=\"introductoryText\">May contain</p>\n<p>Benzalkonium chloride, disodium edetate</p>\n</section>\n<section outputclass=\"medicinalProduct\">\n<title>Optilast 0.05% eye drops <ph outputclass=\"manufacturer\">(Meda Pharmaceuticals Ltd)</ph>\n</title>\n<data name=\"ampid\">3636611000001104</data>\n<p outputclass=\"strengthOfActiveIngredient\">Azelastine hydrochloride 500&#8239;microgram per 1&#8239;ml</p>\n<ul outputclass=\"packs\">\n<li outputclass=\"packSizePriceTariff\">\n<p outputclass=\"packInfo\">\n<ph outputclass=\"packSize\">8</ph>\n<ph outputclass=\"unitOfMeasure\">ml</ph>\n<ph outputclass=\"legalCategory\">POM</ph>\n</p>\n<p outputclass=\"nhsIndicativeInfo\">\n<ph outputclass=\"nhsIndicative\">NHS indicative</ph>\n<ph outputclass=\"priceText\">price =</ph>\n<ph outputclass=\"nhsIndicativePrice\">&#163;6.40</ph>\n</p>\n</li>\n</ul>\n</section>\n</body>\n<parents>\n<xref format=\"dita\" scope=\"local\" type=\"drug\" href=\"#PHP6904\" title=\"AZELASTINE HYDROCHLORIDE\" namespace=\"/drugs/azelastine-hydrochloride\">AZELASTINE HYDROCHLORIDE</xref>\n</parents>\n</topic>",
    "id": "PHP76215",
    "outputclass": "medicinalForm",
    "type": "medicinalForm",
    "namespace": "/drugs/azelastine-hydrochloride/eye-drops",
    "basename": "eye-drops",
    "form": "Eye drops",
    "excipients": [
        "Benzalkonium chloride",
        "disodium edetate"
    ],
    "products": [
        {
            "title": "Optilast 0.05% eye drops (Meda Pharmaceuticals Ltd) ",
            "header": "Optilast 0.05% eye drops <ph outputclass=\"manufacturer\">(Meda Pharmaceuticals Ltd)</ph>",
            "manufacturer": "(Meda Pharmaceuticals Ltd)",
            "name": "Optilast 0.05% eye drops",
            "ampid": "3636611000001104",
            "strengthOfActiveIngredient": "Azelastine hydrochloride 500 microgram per 1 ml",
            "packs": [
                {
                    "textContent": " 8 ml POM ",
                    "html": "<ph outputclass=\"packSize\">8</ph> <ph outputclass=\"unitOfMeasure\">ml</ph> <ph outputclass=\"legalCategory\">POM</ph>",
                    "packSize": "8",
                    "unitOfMeasure": "ml",
                    "legalCategory": "POM",
                    "nhsIndicativeInfo": {
                        "textContent": " NHS indicative price = &#163;6.40 ",
                        "html": "<ph outputclass=\"nhsIndicative\">NHS indicative</ph> <ph outputclass=\"priceText\">price =</ph> <ph outputclass=\"nhsIndicativePrice\">&#163;6.40</ph>",
                        "nhsIndicativePrice": "&#163;6.40"
                    }
                }
            ]
        }
    ],
    "parent": {
        "id": "PHP6904",
        "label": "AZELASTINE HYDROCHLORIDE"
    }
}